costools/__init__.py
costools/add_cos_s_region.py
costools/costoolsutil.py
costools/saamodel.py
costools/splittag.help
costools/splittag.py
costools/timefilter.help
costools/timefilter.py
costools/version.py
costools/x1dcorr.help
costools/x1dcorr.py
costools/pars/splittag.cfg
costools/pars/splittag.cfgspc
costools/pars/timefilter.cfg
costools/pars/timefilter.cfgspc
costools/pars/x1dcorr.cfg
costools/pars/x1dcorr.cfgspc
costools/tests/__init__.py
costools/tests/test_noop.py
costools-1.2.6.data/scripts/add_cos_s_region.py
costools-1.2.6.dist-info/LICENSE.txt
costools-1.2.6.dist-info/METADATA
costools-1.2.6.dist-info/WHEEL
costools-1.2.6.dist-info/entry_points.txt
costools-1.2.6.dist-info/top_level.txt
costools-1.2.6.dist-info/RECORD
