Metadata-Version: 2.1
Name: costools
Version: 1.2.6
Summary: Tools for COS (Cosmic Origins Spectrograph)
Home-page: https://github.com/spacetelescope/costools
Author: Warren Hack, Nadezhda Dencheva, Phil Hodge
Author-email: help@stsci.edu
License: BSD
Classifier: Intended Audience :: Science/Research
Classifier: License :: OSI Approved :: BSD License
Classifier: Operating System :: OS Independent
Classifier: Programming Language :: Python
Classifier: Topic :: Scientific/Engineering :: Astronomy
Classifier: Topic :: Software Development :: Libraries :: Python Modules
License-File: LICENSE.txt
Requires-Dist: astropy
Requires-Dist: calcos
Requires-Dist: numpy
Requires-Dist: stsci.tools
Provides-Extra: docs
Requires-Dist: sphinx ; extra == 'docs'
Requires-Dist: numpydoc ; extra == 'docs'
Provides-Extra: test
Requires-Dist: pytest ; extra == 'test'
Requires-Dist: pytest-cov ; extra == 'test'
Requires-Dist: codecov ; extra == 'test'
